bin/__init__.py
bin/bm.py
bin/tests.py
natlog/__init__.py
natlog/db.py
natlog/natlog.py
natlog/ndb.py
natlog/neural_natlog.py
natlog/parser.py
natlog/scanner.py
natlog/tdb.py
natlog/textual_natlog.py
natlog/tools.py
natlog/unify.py
natlog/app/__init__.py
natlog/app/natapp.py
natlog/doc/natlog.pdf
natlog/doc/natlog_deep.pdf
natlog/doc/natlog_gpt.pdf
natlog/doc/prolog50.pdf
natlog/doc/slides_ICLP21.pdf
natlog/doc/slides_LPOP22.pdf
natlog/natprogs/arith.nat
natlog/natprogs/dall_e.nat
natlog/natprogs/db.json
natlog/natprogs/db.nat
natlog/natprogs/db.tsv
natlog/natprogs/dbtc.nat
natlog/natprogs/elements.nat
natlog/natprogs/elements.tsv
natlog/natprogs/emu.nat
natlog/natprogs/facts.nat
natlog/natprogs/family.nat
natlog/natprogs/gcol.nat
natlog/natprogs/gram.nat
natlog/natprogs/interclausal.nat
natlog/natprogs/lib.nat
natlog/natprogs/lib_tests.nat
natlog/natprogs/loop.nat
natlog/natprogs/meta.nat
natlog/natprogs/nrev.nat
natlog/natprogs/perm.nat
natlog/natprogs/pro.nat
natlog/natprogs/pro2nat.pro
natlog/natprogs/py_call.nat
natlog/natprogs/py_call1.nat
natlog/natprogs/queens.nat
natlog/natprogs/queens.pro
natlog/natprogs/story.nat
natlog/natprogs/sudoku4.nat
natlog/natprogs/tc.nat
natlog/test/__init__.py
natlog/test/benchmark.py
natlog/test/tests.py
natlog-1.7.2.dist-info/LICENSE
natlog-1.7.2.dist-info/METADATA
natlog-1.7.2.dist-info/WHEEL
natlog-1.7.2.dist-info/top_level.txt
natlog-1.7.2.dist-info/RECORD
