Metadata-Version: 2.1
Name: natlog
Version: 1.7.2
Summary: Prolog-like interpreter and tuple store
Home-page: https://github.com/ptarau/minlog.git
Author: Paul Tarau
Author-email: paul.tarau@gmail.com
License: Apache
License-File: LICENSE
